{
  "requestsFinished": 1,
  "requestsFailed": 0,
  "requestsRetries": 0,
  "requestsFailedPerMinute": 0,
  "requestsFinishedPerMinute": 6,
  "requestMinDurationMillis": 9433,
  "requestMaxDurationMillis": 9433,
  "requestTotalFailedDurationMillis": 0,
  "requestTotalFinishedDurationMillis": 9433,
  "crawlerStartedAt": "2024-10-24T21:17:23.294Z",
  "crawlerFinishedAt": "2024-10-24T21:17:33.145Z",
  "statsPersistedAt": "2024-10-24T21:17:33.145Z",
  "crawlerRuntimeMillis": 10183,
  "crawlerLastStartTimestamp": 1729804642962,
  "requestRetryHistogram": [
    1
  ],
  "statsId": 0,
  "requestAvgFailedDurationMillis": null,
  "requestAvgFinishedDurationMillis": 9433,
  "requestTotalDurationMillis": 9433,
  "requestsTotal": 1,
  "requestsWithStatusCode": {
    "200": 1
  },
  "errors": {},
  "retryErrors": {}
}